README
setup.py
pyipmi/__init__.py
pyipmi/bmc.py
pyipmi/bootdev.py
pyipmi/bootparam.py
pyipmi/channel.py
pyipmi/chassis.py
pyipmi/data.py
pyipmi/dcmi.py
pyipmi/event.py
pyipmi/fabric.py
pyipmi/freeipmi_pef.py
pyipmi/fru.py
pyipmi/fw.py
pyipmi/info.py
pyipmi/lan.py
pyipmi/mc.py
pyipmi/pef.py
pyipmi/pet.py
pyipmi/sdr.py
pyipmi/sel.py
pyipmi/server.py
pyipmi/sol.py
pyipmi/user.py
pyipmi/watchdog.py
pyipmi.egg-info/PKG-INFO
pyipmi.egg-info/SOURCES.txt
pyipmi.egg-info/dependency_links.txt
pyipmi.egg-info/requires.txt
pyipmi.egg-info/top_level.txt
pyipmi/commands/__init__.py
pyipmi/commands/bmc.py
pyipmi/commands/bootdev.py
pyipmi/commands/bootparam.py
pyipmi/commands/channel.py
pyipmi/commands/chassis.py
pyipmi/commands/data.py
pyipmi/commands/dcmi.py
pyipmi/commands/event.py
pyipmi/commands/fabric.py
pyipmi/commands/fabric_config.py
pyipmi/commands/freeipmi_pef.py
pyipmi/commands/fru.py
pyipmi/commands/fw.py
pyipmi/commands/info.py
pyipmi/commands/lan.py
pyipmi/commands/mc.py
pyipmi/commands/payload.py
pyipmi/commands/pef.py
pyipmi/commands/pet.py
pyipmi/commands/pmic.py
pyipmi/commands/sdr.py
pyipmi/commands/sel.py
pyipmi/commands/sol.py
pyipmi/commands/user.py
pyipmi/commands/watchdog.py
pyipmi/tools/__init__.py
pyipmi/tools/ipmi_pef_config.py
pyipmi/tools/ipmi_pet.py
pyipmi/tools/ipmidcmi.py
pyipmi/tools/ipmitool.py
pyipmi/tools/responseparser.py