Metadata-Version: 1.1
Name: pyipmi
Version: 0.9.2
Summary: Wrapper for IPMI clients
Home-page: UNKNOWN
Author: Calxeda
Author-email: UNKNOWN
License: UNKNOWN
Platform: UNKNOWN
Classifier: License :: OSI Approved :: BSD License
Classifier: Programming Language :: Python :: 2.7
